quilt_mcp/__init__.py
quilt_mcp/config.py
quilt_mcp/constants.py
quilt_mcp/formatting.py
quilt_mcp/health.py
quilt_mcp/main.py
quilt_mcp/runtime_context.py
quilt_mcp/utils.py
quilt_mcp/version_sync.py
quilt_mcp/models/__init__.py
quilt_mcp/models/inputs.py
quilt_mcp/models/responses.py
quilt_mcp/optimization/__init__.py
quilt_mcp/optimization/autonomous.py
quilt_mcp/optimization/integration.py
quilt_mcp/optimization/interceptor.py
quilt_mcp/optimization/scenarios.py
quilt_mcp/optimization/testing.py
quilt_mcp/resources/__init__.py
quilt_mcp/resources/admin.py
quilt_mcp/resources/athena.py
quilt_mcp/resources/auth.py
quilt_mcp/resources/base.py
quilt_mcp/resources/metadata.py
quilt_mcp/resources/permissions.py
quilt_mcp/resources/tabulator.py
quilt_mcp/resources/workflow.py
quilt_mcp/search/__init__.py
quilt_mcp/search/backends/__init__.py
quilt_mcp/search/backends/base.py
quilt_mcp/search/backends/elasticsearch.py
quilt_mcp/search/backends/graphql.py
quilt_mcp/search/backends/s3.py
quilt_mcp/search/core/__init__.py
quilt_mcp/search/core/query_parser.py
quilt_mcp/search/tools/__init__.py
quilt_mcp/search/tools/search_explain.py
quilt_mcp/search/tools/search_suggest.py
quilt_mcp/search/tools/unified_search.py
quilt_mcp/search/utils/__init__.py
quilt_mcp/services/__init__.py
quilt_mcp/services/athena_read_service.py
quilt_mcp/services/athena_service.py
quilt_mcp/services/auth_metadata.py
quilt_mcp/services/auth_service.py
quilt_mcp/services/bearer_auth_service.py
quilt_mcp/services/governance_service.py
quilt_mcp/services/jwt_decoder.py
quilt_mcp/services/metadata_service.py
quilt_mcp/services/permission_discovery.py
quilt_mcp/services/permissions_service.py
quilt_mcp/services/quilt_service.py
quilt_mcp/services/tabulator_service.py
quilt_mcp/services/workflow_service.py
quilt_mcp/telemetry/__init__.py
quilt_mcp/telemetry/collector.py
quilt_mcp/telemetry/metrics.py
quilt_mcp/telemetry/privacy.py
quilt_mcp/telemetry/transport.py
quilt_mcp/tools/__init__.py
quilt_mcp-0.8.5.dist-info/LICENSE.txt
quilt_mcp-0.8.5.dist-info/METADATA
quilt_mcp-0.8.5.dist-info/WHEEL
quilt_mcp-0.8.5.dist-info/entry_points.txt
quilt_mcp-0.8.5.dist-info/top_level.txt
quilt_mcp-0.8.5.dist-info/RECORD
