Metadata-Version: 2.1
Name: quilt-mcp
Version: 0.8.5
Summary: Secure MCP server for accessing Quilt data with JWT authentication
Author-email: Quilt Data <support@quilt.bio>
Maintainer-email: Quilt Data <support@quilt.bio>
License: Apache License
Project-URL: Homepage, https://github.com/quiltdata/quilt-mcp-server
Project-URL: Repository, https://github.com/quiltdata/quilt-mcp-server
Project-URL: Issues, https://github.com/quiltdata/quilt-mcp-server/issues
Project-URL: Documentation, https://github.com/quiltdata/quilt-mcp-server/blob/main/README.md
Keywords: mcp,model-context-protocol,claude,quilt,data,analytics,science,server,aws,s3,authentication
Classifier: Development Status :: 4 - Beta
Classifier: Intended Audience :: Developers
Classifier: Operating System :: OS Independent
Classifier: Programming Language :: Python :: 3
Classifier: Programming Language :: Python :: 3.11
Classifier: Programming Language :: Python :: 3.12
Classifier: Topic :: Software Development :: Libraries :: Python Modules
Classifier: Topic :: Scientific/Engineering :: Information Analysis
Requires-Python: >=3.11
License-File: LICENSE.txt
Requires-Dist: quilt3>=5.6.0
Requires-Dist: fastmcp>=2.12.4
Requires-Dist: mcp>=1.12.0
Requires-Dist: boto3>=1.34.0
Requires-Dist: httpx>=0.27.0
Requires-Dist: cachetools>=5.3.0
Requires-Dist: matplotlib>=3.7.0
Requires-Dist: numpy>=1.24.0
Requires-Dist: pandas>=2.0.0
Requires-Dist: plotly>=5.15.0
Requires-Dist: altair>=5.0.0
Requires-Dist: pysam>=0.21.0
Requires-Dist: biopython>=1.81
Requires-Dist: pybedtools>=0.9.0
Requires-Dist: pybigwig>=0.3.18
Requires-Dist: sqlalchemy>=2.0.0
Requires-Dist: pyathena>=3.0.0
Requires-Dist: PyYAML>=6.0.0
Requires-Dist: pyjwt>=2.8.0
